sigma/backends/QRadarAQL/QRadarAQL.py
sigma/backends/QRadarAQL/__init__.py
sigma/mapping/fields.py
sigma/mapping/logsources.py
sigma/mapping/products.py
sigma/mapping/services.py
sigma/pipelines/QRadarAQL/QRadarAQL.py
sigma/pipelines/QRadarAQL/__init__.py
sigma/pySigma_QRadar_base/.git
sigma/pySigma_QRadar_base/LICENSE
sigma/pySigma_QRadar_base/QRadarBackend.py
sigma/pySigma_QRadar_base/QRadarFieldsPipeline.py
sigma/pySigma_QRadar_base/QRadarPayloadPipeline.py
sigma/pySigma_QRadar_base/QRadarPipeline.py
sigma/pySigma_QRadar_base/README.md
sigma/pySigma_QRadar_base/generate_readme_mapping.py
sigma/pySigma_QRadar_base/poetry.lock
sigma/pySigma_QRadar_base/pyproject.toml
pysigma_backend_qradar_aql-0.3.2.dist-info/LICENSE
pysigma_backend_qradar_aql-0.3.2.dist-info/METADATA
pysigma_backend_qradar_aql-0.3.2.dist-info/WHEEL
pysigma_backend_qradar_aql-0.3.2.dist-info/RECORD
