Metadata-Version: 2.1
Name: pySigma-backend-QRadar-AQL
Version: 0.3.2
Summary: pySigma QRadarAQL backend
Home-page: https://github.com/IBM/pySigma-backend-QRadar-AQL
License: MIT
Author: IBM
Author-email: noaakless@gmail.com
Requires-Python: >=3.8,<4.0
Classifier: License :: OSI Approved :: MIT License
Classifier: Programming Language :: Python :: 3
Classifier: Programming Language :: Python :: 3.8
Classifier: Programming Language :: Python :: 3.9
Classifier: Programming Language :: Python :: 3.10
Classifier: Programming Language :: Python :: 3.11
Classifier: Programming Language :: Python :: 3.12
Requires-Dist: pysigma (>=0.9.8,<0.12.0)
Requires-Dist: regex (>=2023.12.25,<2024.0.0)
Project-URL: Repository, https://github.com/IBM/pySigma-backend-QRadar-AQL
